.DS_Store
huilin/__init__.py
huilin/myprint.py
twosyshuilin-1.1.1.dist-info/METADATA
twosyshuilin-1.1.1.dist-info/WHEEL
twosyshuilin-1.1.1.dist-info/top_level.txt
twosyshuilin-1.1.1.dist-info/RECORD
