Metadata-Version: 2.1
Name: twosyshuilin
Version: 1.1.1
Summary: A print test for PyPI
Home-page: https://www.python.org/
Author: winycg
License: UNKNOWN
Platform: UNKNOWN
Requires-Python: >=3
